fairness_garvit/__init__.py
fairness_garvit/fairness_model.py
fairness_garvit-0.1.1.dist-info/METADATA
fairness_garvit-0.1.1.dist-info/WHEEL
fairness_garvit-0.1.1.dist-info/top_level.txt
fairness_garvit-0.1.1.dist-info/RECORD
